aoiki18n/aoiki18n_.py
aoiki18n/__init__.py
AoikI18n-0.1.0.dist-info/DESCRIPTION.rst
AoikI18n-0.1.0.dist-info/METADATA
AoikI18n-0.1.0.dist-info/metadata.json
AoikI18n-0.1.0.dist-info/RECORD
AoikI18n-0.1.0.dist-info/top_level.txt
AoikI18n-0.1.0.dist-info/WHEEL
