Metadata-Version: 2.0
Name: AoikI18n
Version: 0.1.0
Summary: A simple I18n solution featuring fallback locale, YAML locale file, synonym locale file, and flexible locale file path.
Home-page: https://github.com/AoiKuiyuyou/AoikI18n
Author: Aoi.Kuiyuyou
Author-email: aoi.kuiyuyou@google.com
License: MIT
Keywords: i18n locale fallback yaml synonym flexible file path
Platform: UNKNOWN
Classifier: Development Status :: 3 - Alpha
Classifier: Intended Audience :: Developers
Classifier: License :: OSI Approved :: MIT License
Classifier: Operating System :: OS Independent
Classifier: Programming Language :: Python :: 2
Classifier: Programming Language :: Python :: 2.6
Classifier: Programming Language :: Python :: 2.7
Classifier: Programming Language :: Python :: 3
Classifier: Programming Language :: Python :: 3.1
Classifier: Programming Language :: Python :: 3.2
Classifier: Programming Language :: Python :: 3.3
Classifier: Programming Language :: Python :: 3.4
Requires-Dist: pyyaml
